[{"MAPPING":[{"CONTENTTYPE":"TIMESTAMP","FORMATTYPE":"EN","LENGTH":538976339,"LONGNAME":"","MR":"","SHORTNAME":"personnel-data","TYPE-CONVERSION":538976288},{"CONTENTTYPE":"","FORMATTYPE":"CY","LENGTH":538976288,"LONGNAME":"","MR":"","SHORTNAME":"personnel-id","TYPE-CONVERSION":538976288},{"CONTENTTYPE":"","FORMATTYPE":"-S","LENGTH":538976288,"LONGNAME":"","MR":"","SHORTNAME":"id-data","TYPE-CONVERSION":538976288},{"CONTENTTYPE":"","FORMATTYPE":"AL","LENGTH":760234317,"LONGNAME":"","MR":"","SHORTNAME":"personnel-no","TYPE-CONVERSION":538976288},{"CONTENTTYPE":"","FORMATTYPE":"AR","LENGTH":1230262351,"LONGNAME":"","MR":"","SHORTNAME":"id-card","TYPE-CONVERSION":538976288},{"CONTENTTYPE":"","FORMATTYPE":"Y","LENGTH":542330447,"LONGNAME":"","MR":"","SHORTNAME":"signature","TYPE-CONVERSION":538976288},{"CONTENTTYPE":"","FORMATTYPE":"","LENGTH":538976288,"LONGNAME":"","MR":"","SHORTNAME":"full-name","TYPE-CONVERSION":538976288},{"CONTENTTYPE":"","FORMATTYPE":"","LENGTH":538976288,"LONGNAME":"","MR":"","SHORTNAME":"first-name","TYPE-CONVERSION":538976288},{"CONTENTTYPE":"","FORMATTYPE":"","LENGTH":1162104393,"LONGNAME":"","MR":"","SHORTNAME":"middle-name","TYPE-CONVERSION":538976288},{"CONTENTTYPE":"","FORMATTYPE":"","LENGTH":538976344,"LONGNAME":"","MR":"","SHORTNAME":"name","TYPE-CONVERSION":538976288},{"CONTENTTYPE":"","FORMATTYPE":"","LENGTH":538976288,"LONGNAME":"","MR":"","SHORTNAME":"mar-stat","TYPE-CONVERSION":538976288},{"CONTENTTYPE":"","FORMATTYPE":"","LENGTH":538976288,"LONGNAME":"","MR":"","SHORTNAME":"sex","TYPE-CONVERSION":538976288},{"CONTENTTYPE":"","FORMATTYPE":"","LENGTH":538976288,"LONGNAME":"","MR":"","SHORTNAME":"birth","TYPE-CONVERSION":538976288},{"CONTENTTYPE":"","FORMATTYPE":"","LENGTH":1162104393,"LONGNAME":"","MR":"","SHORTNAME":"private-address","TYPE-CONVERSION":538976288},{"CONTENTTYPE":"","FORMATTYPE":"","LENGTH":1229335896,"LONGNAME":"","MR":"","SHORTNAME":"p-address-line","TYPE-CONVERSION":538976288},{"CONTENTTYPE":"","FORMATTYPE":"","LENGTH":538985804,"LONGNAME":"","MR":"","SHORTNAME":"p-city","TYPE-CONVERSION":538976288},{"CONTENTTYPE":"","FORMATTYPE":"","LENGTH":538976288,"LONGNAME":"","MR":"","SHORTNAME":"p-post-code","TYPE-CONVERSION":538976288},{"CONTENTTYPE":"","FORMATTYPE":"","LENGTH":538976288,"LONGNAME":"","MR":"","SHORTNAME":"p-country","TYPE-CONVERSION":538976288},{"CONTENTTYPE":"","FORMATTYPE":"","LENGTH":1162104393,"LONGNAME":"","MR":"\u0004\u0000\u0000\u0000}\ufffd5bX\u0012\u0000\u0000~\ufffd5bX\u0012\u0000\u0000;\ufffd5bX\u0012","SHORTNAME":"p-phone-email","TYPE-CONVERSION":538976288},{"CONTENTTYPE":"","FORMATTYPE":"","LENGTH":1094987096,"LONGNAME":"","MR":"\ufffd5bX\u0012\u0000\u0000\u001a\u0000\u0000\u0000Generated","SHORTNAME":"p-area-code","TYPE-CONVERSION":538976288},{"CONTENTTYPE":"","FORMATTYPE":"","LENGTH":1094861140,"LONGNAME":"","MR":"Host                Da","SHORTNAME":"private-phone","TYPE-CONVERSION":538976288},{"CONTENTTYPE":"","FORMATTYPE":"","LENGTH":538985811,"LONGNAME":"","MR":"e                Version             Location            Directory           Filename            absoluteFilename","SHORTNAME":"private-fax","TYPE-CONVERSION":538976288},{"CONTENTTYPE":"","FORMATTYPE":"","LENGTH":538976288,"LONGNAME":"","MR":"Type                Size","SHORTNAME":"private-mobile","TYPE-CONVERSION":538976288},{"CONTENTTYPE":"","FORMATTYPE":"","LENGTH":1347436877,"LONGNAME":"","MR":"MimeType            Da","SHORTNAME":"private-email","TYPE-CONVERSION":538976288},{"CONTENTTYPE":"\u0001\u0000\u0000\u0000\ufffd\ufffd5bX\u0012\u0000\u0000\"\u0000\u0000\u0000PERS","FORMATTYPE":"","LENGTH":541544009,"LONGNAME":"","MR":"a                Thumbnail           Picture             Checksum            ThumbnailSHAchecksumPictureSHAchecksum","SHORTNAME":"business-address","TYPE-CONVERSION":538976288},{"CONTENTTYPE":"ONNEL-ID        FULL","FORMATTYPE":"","LENGTH":538976288,"LONGNAME":"","MR":"EXIFinformation     Model","SHORTNAME":"b-address-line","TYPE-CONVERSION":538976288},{"CONTENTTYPE":"-NAME           FIRS","FORMATTYPE":"","LENGTH":538976288,"LONGNAME":"","MR":"Orientation         Da","SHORTNAME":"b-city","TYPE-CONVERSION":538976288},{"CONTENTTYPE":"T-NAME          NAME","FORMATTYPE":"","LENGTH":538976288,"LONGNAME":"","MR":"eExif            DateOriginal        ExposureTime        F-Number            Width               Height","SHORTNAME":"b-post-code","TYPE-CONVERSION":538976288},{"CONTENTTYPE":"MIDD","FORMATTYPE":"","LENGTH":1380927571,"LONGNAME":"","MR":"","SHORTNAME":"b-country","TYPE-CONVERSION":538976288},{"CONTENTTYPE":"LE-I            MAR-","FORMATTYPE":"","LENGTH":1296125524,"LONGNAME":"","MR":"","SHORTNAME":"room_number","TYPE-CONVERSION":538976288},{"CONTENTTYPE":"STAT            SEX","FORMATTYPE":"","LENGTH":538976325,"LONGNAME":"","MR":"","SHORTNAME":"b-phone-email","TYPE-CONVERSION":538976288},{"CONTENTTYPE":"BIRT","FORMATTYPE":"","LENGTH":538976288,"LONGNAME":"","MR":"charset=UTF-8       charse","SHORTNAME":"b-area-code","TYPE-CONVERSION":538976288},{"CONTENTTYPE":"H               FULL","FORMATTYPE":"","LENGTH":538976288,"LONGNAME":"","MR":"=UTF-8       charset=UTF-8                                               charset=UTF-8","SHORTNAME":"business-phone","TYPE-CONVERSION":538976288},{"CONTENTTYPE":"-ADDRESS        ADDR","FORMATTYPE":"","LENGTH":1162893652,"LONGNAME":"","MR":"","SHORTNAME":"business-fax","TYPE-CONVERSION":538976288},{"CONTENTTYPE":"ESS-LINE        CITY","FORMATTYPE":"","LENGTH":1313817389,"LONGNAME":"","MR":"","SHORTNAME":"business-mobile","TYPE-CONVERSION":538976288},{"CONTENTTYPE":"ZIP","FORMATTYPE":"","LENGTH":1397900630,"LONGNAME":"","MR":"","SHORTNAME":"business-email","TYPE-CONVERSION":538976288},{"CONTENTTYPE":"COUN","FORMATTYPE":"","LENGTH":542003017,"LONGNAME":"","MR":"charset=UT","SHORTNAME":"job-title","TYPE-CONVERSION":538976288},{"CONTENTTYPE":"TRY             TELE","FORMATTYPE":"","LENGTH":538976288,"LONGNAME":"","MR":"-8       charset=UTF-8       charset=UTF-8       charset=UTF-8","SHORTNAME":"income","TYPE-CONVERSION":538976288},{"CONTENTTYPE":"PHONE           AREA","FORMATTYPE":"","LENGTH":1196314444,"LONGNAME":"","MR":"harset=UTF-8       charset=UTF-8       charset=UTF-8       charset=UTF-8       \u0002\u0000\u0000\u0000{\ufffd5bX\u0012\u0000\u0000\u003e\ufffd5bX\u0012","SHORTNAME":"curr-code","TYPE-CONVERSION":538976288},{"CONTENTTYPE":"-CODE           PHON","FORMATTYPE":"","LENGTH":1162690894,"LONGNAME":"","MR":"\u000e\u0000\u0000\u0000REG-NUM             CHASSIS-NUM         PERSONNEL-ID        CAR-DETAILS         MAKE                MODEL               COLOR               YEAR                CLASS               LEASE-PUR           DATE-ACQ            CURR-CODE           MAINT-COST","SHORTNAME":"salary","TYPE-CONVERSION":538976288},{"CONTENTTYPE":"E               DEPT","FORMATTYPE":"","LENGTH":538976288,"LONGNAME":"","MR":"MODEL-YEAR-MAKE","SHORTNAME":"bonus","TYPE-CONVERSION":538976288},{"CONTENTTYPE":"JOB-","FORMATTYPE":"","LENGTH":538976288,"LONGNAME":"","MR":"","SHORTNAME":"total-income","TYPE-CONVERSION":538976288},{"CONTENTTYPE":"TITLE           INCO","FORMATTYPE":"","LENGTH":538976288,"LONGNAME":"","MR":"","SHORTNAME":"leave-date","TYPE-CONVERSION":538976288},{"CONTENTTYPE":"ME              CURR","FORMATTYPE":"","LENGTH":1196311884,"LONGNAME":"","MR":"","SHORTNAME":"leave-due","TYPE-CONVERSION":538976288},{"CONTENTTYPE":"-CODE           SALA","FORMATTYPE":"","LENGTH":538986580,"LONGNAME":"","MR":"","SHORTNAME":"leave-taken","TYPE-CONVERSION":538976288},{"CONTENTTYPE":"RY              BONU","FORMATTYPE":"","LENGTH":538976288,"LONGNAME":"","MR":"","SHORTNAME":"leave-booked","TYPE-CONVERSION":538976288},{"CONTENTTYPE":"S               LEAV","FORMATTYPE":"","LENGTH":538976288,"LONGNAME":"\u0002\u0000\u0000\u0000I\ufffd5bX\u0012","MR":"","SHORTNAME":"leave-start","TYPE-CONVERSION":538976288},{"CONTENTTYPE":"E-DATA          LEAV","FORMATTYPE":"","LENGTH":538976288,"LONGNAME":"e\ufffd5bX\u0012\u0000\u0000\u0017\u0000\u0000\u0000TYPE-GRO","MR":"","SHORTNAME":"leave-end","TYPE-CONVERSION":538976288},{"CONTENTTYPE":"E-DUE           LEAV","FORMATTYPE":"","LENGTH":1414418243,"LONGNAME":"UP          TYPE","MR":"","SHORTNAME":"language","TYPE-CONVERSION":538976288},{"CONTENTTYPE":"E-TAKEN         LEAV","FORMATTYPE":"","LENGTH":1414811205,"LONGNAME":"GENERATE","MR":"\u0001\u0000\u0000\u0000\ufffd\ufffd5bX\u0012","SHORTNAME":"last-update","TYPE-CONVERSION":538976288},{"CONTENTTYPE":"E-BOOKED        LEAV","FORMATTYPE":"","LENGTH":541413465,"LONGNAME":"D           HOST","MR":"\n\u0000\u0000\u0000Id                  Name                FirstName           LastName            Income              Salary              Bonus               Department          JobTitle            City","SHORTNAME":"picture","TYPE-CONVERSION":538976288},{"CONTENTTYPE":"E-START         LEAV","FORMATTYPE":"","LENGTH":538976288,"LONGNAME":"DATE","MR":"","SHORTNAME":"documents","TYPE-CONVERSION":538976288},{"CONTENTTYPE":"E-END           LANG","FORMATTYPE":"","LENGTH":538976288,"LONGNAME":"VERSION","MR":"","SHORTNAME":"document-description","TYPE-CONVERSION":538976288},{"CONTENTTYPE":"PH","FORMATTYPE":"","LENGTH":1297239878,"LONGNAME":"LOCATION","MR":"","SHORTNAME":"document-type","TYPE-CONVERSION":538976288},{"CONTENTTYPE":"LEAV","FORMATTYPE":"","LENGTH":1498698817,"LONGNAME":"FILE-NR","MR":"","SHORTNAME":"document","TYPE-CONVERSION":538976288},{"CONTENTTYPE":"E-LEFT          DEPA","FORMATTYPE":"","LENGTH":538985808,"LONGNAME":"DATA-DAT","MR":"\u0001\u0000\u0000\u0000\ufffd\ufffd5bX\u0012","SHORTNAME":"creation_time","TYPE-CONVERSION":538976288},{"CONTENTTYPE":"RTMENT          DEPT","FORMATTYPE":"","LENGTH":538976288,"LONGNAME":"ABASE       MAPNAME","MR":"\u0003\u0000\u0000\u0000Vendor              Model               Color                                                                           \u0001\u0000\u0000\u0000\ufffd\ufffd5bX\u0012","SHORTNAME":"Last_Updates","TYPE-CONVERSION":538976288},{"CONTENTTYPE":"-PERSON         CURR","FORMATTYPE":"","LENGTH":538976288,"LONGNAME":"MAP-FLAG","MR":"","SHORTNAME":"","TYPE-CONVERSION":538976288}],"TIMESTAMP":[]},{"MAPPING":[],"TIMESTAMP":[]},{"MAPPING":[],"TIMESTAMP":[]},{"MAPPING":[],"TIMESTAMP":[]},{"MAPPING":[],"TIMESTAMP":[]},{"MAPPING":[],"TIMESTAMP":[]},{"MAPPING":[],"TIMESTAMP":[]}]